sample/__init__.py
sample/package_data.dat
sample/simple.py
conradbzura_sample_project-0.4.dist-info/METADATA
conradbzura_sample_project-0.4.dist-info/WHEEL
conradbzura_sample_project-0.4.dist-info/top_level.txt
conradbzura_sample_project-0.4.dist-info/RECORD
